{
    "id":  "artifact_105",
    "name":  "白玉透雕花囊",
    "era":  "清代",
    "category":  "玉器",
    "museum":  "故宫博物院",
    "origin":  "北京",
    "description":  "透雕多层结构玉器，装饰梅鹤山水人物。",
    "features":  [
                     "透雕",
                     "多层结构",
                     "山水人物"
                 ],
    "value_points":  [
                         "玉雕工艺",
                         "艺术性强"
                     ],
    "image":  "jade_pouch.jpg",
    "image_caption":  "花囊",
    "keywords":  [
                     "玉雕",
                     "透雕"
                 ],
    "qa_pairs":  [
                     {
                         "q":  "如果只看核心特征，应该怎么理解这件文物？",
                         "a":  "白玉透雕花囊可概括为：清代、玉器、透雕。",
                         "keywords":  [
                                          "白玉透雕花囊",
                                          "清代",
                                          "玉器"
                                      ]
                     },
                     {
                         "q":  "换个说法，它最核心的信息是什么？",
                         "a":  "白玉透雕花囊可概括为：清代、玉器、透雕。",
                         "keywords":  [
                                          "白玉透雕花囊",
                                          "清代",
                                          "玉器"
                                      ]
                     },
                     {
                         "q":  "你可以把它概括得更口语一点吗？",
                         "a":  "白玉透雕花囊可概括为：清代、玉器、透雕。",
                         "keywords":  [
                                          "白玉透雕花囊",
                                          "清代",
                                          "玉器"
                                      ]
                     },
                     {
                         "q":  "如果我只想记住三个点，应该记什么？",
                         "a":  "白玉透雕花囊可概括为：清代、玉器、透雕。",
                         "keywords":  [
                                          "白玉透雕花囊",
                                          "清代",
                                          "玉器"
                                      ]
                     },
                     {
                         "q":  "能说说它的文化、艺术或研究价值吗？",
                         "a":  "白玉透雕花囊值得关注，因为它具有玉雕工艺、艺术性强。",
                         "keywords":  [
                                          "白玉透雕花囊",
                                          "清代",
                                          "玉器"
                                      ]
                     },
                     {
                         "q":  "它为什么值得关注？",
                         "a":  "白玉透雕花囊值得关注，因为它具有玉雕工艺、艺术性强。",
                         "keywords":  [
                                          "白玉透雕花囊",
                                          "清代",
                                          "玉器"
                                      ]
                     }
                 ]
}